starlette_session/__init__.py
starlette_session/backends.py
starlette_session/interfaces.py
starlette_session-0.4.1.dist-info/LICENSE.md
starlette_session-0.4.1.dist-info/WHEEL
starlette_session-0.4.1.dist-info/METADATA
starlette_session-0.4.1.dist-info/RECORD
