Metadata-Version: 2.1
Name: starlette-session
Version: 0.4.1
Summary: A library for backend side session with starlette
Home-page: https://github.com/auredentan/starlette-sessionhttps://github.com/auredentan/starlette-session
License: MIT
Author: Aurélien Dentan
Author-email: aurelien.dentan@gmail.com
Maintainer: Aurélien Dentan
Maintainer-email: aurelien.dentan@gmail.com
Requires-Python: >=3.6.1,<4.0.0
Classifier: License :: OSI Approved :: MIT License
Classifier: Programming Language :: Python :: 3
Classifier: Programming Language :: Python :: 3.7
Classifier: Programming Language :: Python :: 3.8
Classifier: Topic :: Software Development :: Libraries :: Python Modules
Provides-Extra: aioredis
Provides-Extra: pymemcache
Provides-Extra: redis
Requires-Dist: aioredis (>=1.3.1,<2.0.0); extra == "aioredis"
Requires-Dist: itsdangerous (>=1.1.0,<2.0.0)
Requires-Dist: pymemcache (>=3.3.0,<4.0.0); extra == "pymemcache"
Requires-Dist: redis (>=3.5.3,<4.0.0); extra == "redis"
Requires-Dist: starlette (>=0.13.8,<0.14.0)
Project-URL: Repository, https://github.com/auredentan/starlette-sessionhttps://github.com/auredentan/starlette-session
